bitable/__init__.py
bitable/__version__.py
bitable/auth.py
bitable/bitable.py
bitable/contact.py
bitable/document.py
bitable/params.py
bitable/spreadsheets.py
bitable/__pycache__/auth.cpython-38.pyc
bitable/__pycache__/params.cpython-38.pyc
python_sdk_bitable-0.1.2.dist-info/LICENSE
python_sdk_bitable-0.1.2.dist-info/METADATA
python_sdk_bitable-0.1.2.dist-info/WHEEL
python_sdk_bitable-0.1.2.dist-info/top_level.txt
python_sdk_bitable-0.1.2.dist-info/RECORD
