Metadata-Version: 2.1
Name: python-sdk-bitable
Version: 0.1.2
Summary: Python sdk for 飞书多维表格
Home-page: https://github.com/me/myproject
Author: liushengyi
Author-email: liuwenxuan123@qq.com
License: MIT
Platform: UNKNOWN
Classifier: License :: OSI Approved :: MIT License
Classifier: Programming Language :: Python
Classifier: Programming Language :: Python :: 3
Classifier: Programming Language :: Python :: 3.6
Classifier: Programming Language :: Python :: Implementation :: CPython
Classifier: Programming Language :: Python :: Implementation :: PyPy
Requires-Python: >=3.6.5
License-File: LICENSE
Requires-Dist: requests
